Workbook

Sheet Leyenda
A1: Product Backlog del proyecto de grado
A2: Plataforma web y móvil con recomendaciones personalizadas para la gestión de eventos y promoción turística de Santander
A4: CÓMO SE USA
A5: 1 | B5: En la hoja 'Product Backlog' están las historias de usuario ordenadas por sprint (de 2 semanas). Mueve el estado de cada una a 'En curso' o 'Terminada'.
A6: 2 | B6: En la hoja 'Sprints' se ve, por sprint, cuántas horas tienes disponibles, cuántas planificaste y cuánto has terminado. Si dice 'Sobrecargado', mueve historias al sprint siguiente o recorta alcance.
A7: 3 | B7: Para Trello: copia la columna B ('Tarjeta') de una selección de filas y pégala en 'Añadir tarjeta'; Trello ofrece crear una tarjeta por línea. Después copia la historia y el criterio en la descripción de cada tarjeta.
A8: 4 | B8: Las historias 'Si hay tiempo' no hacen parte del MVP: solo se trabajan si sobran horas.
A10: FECHAS CLAVE
A11: Acta de aprobación de la propuesta | B11: 46308
A12: Primera fecha para cargar el F-DC-125 | B12: 46398
A13: Fecha máxima para cargar el F-DC-125 | B13: 46488
A14: Días que faltan para la fecha máxima | B14: =B13-TODAY() -> 172
A15: Fin del último sprint | B15: =Sprints!C12 -> 46474
A16: Días de margen entre el último sprint y la fecha máxima | B16: =B13-B15 -> 14
A17: Fuente de las fechas | B17: Correo del Comité de Trabajos de Grado del 14/10/2026 (dato entregado por la estudiante).
A19: RESUMEN DE HORAS
A20: Horas planificadas en sprints (MVP) | B20: =Sprints!F13 -> 147
A21: Horas disponibles según los sprints | B21: =Sprints!E13 -> 148
A22: Horas de historias 'Si hay tiempo' | B22: =SUMIFS('Product Backlog'!H2:H60,'Product Backlog'!G2:G60,"No") -> 13
A24: SUPUESTOS (revísalos y cámbialos)
A25: Horas estimadas por historia | B25: Son estimaciones aproximadas de la asistente, no datos oficiales. Cambia las celdas azules de la columna 'Horas estimadas' cuando veas cuánto te toma cada tarea.
A26: Horas disponibles por sprint | B26: Supuesto: unas 4 horas por semana en requisitos y diseño, unas 10 en el desarrollo (sprints 6 a 8) y unas 7 en las pruebas y el cierre. Son las celdas azules de la hoja 'Sprints'.
A27: Fecha de inicio del sprint 1 | B27: Supuesto: lunes 26 de octubre de 2026. Es la celda amarilla de la hoja 'Sprints'; las demás fechas se calculan a partir de ella.
A28: Plan base | B28: Plan de actividades de la propuesta aprobada: 22 semanas, o 11 sprints de 2 semanas.
A29: Alcance del MVP | B29: Tomado del alcance de la propuesta: versión web para el organizador, versión móvil para el visitante, reservas sin pagos y recomendaciones por reglas.
A31: COLORES
A32: Texto azul | B32: Dato que puedes cambiar (horas, sprint, fecha de inicio).
A33: Texto negro | B33: Fórmula o texto fijo: no lo cambies.

Sheet Product Backlog
A1: ID | B1: Tarjeta (título corto) | C1: Épica | D1: Historia de usuario | E1: Criterio de aceptación | F1: Prioridad | G1: MVP | H1: Horas estimadas | I1: Sprint | J1: Estado
A2: HU-01 | B2: Repositorio, tablero y entorno | C2: Gestión y planificación | D2: Como estudiante, quiero crear el repositorio, el tablero y el entorno de desarrollo, para empezar a construir la plataforma. | E2: Repositorio en GitHub; tablero con este backlog; Node.js, PostgreSQL con PostGIS, Flutter y React funcionando. | F2: Alta | G2: Sí | H2: 3 | I2: 1 | J2: Pendiente
A3: HU-02 | B3: Entrevistas a organizadores | C3: Requisitos | D3: Como estudiante, quiero entrevistar a 3 a 5 organizadores a distancia, para conocer cómo publican sus eventos y manejan las reservas. | E3: Notas anonimizadas ("Organizador 1", etc.) y consentimiento de cada participante guardados. | F3: Alta | G3: Sí | H3: 5 | I3: 1 | J3: Pendiente
A4: HU-03 | B4: Documento de requerimientos | C4: Requisitos | D4: Como estudiante, quiero documentar los requerimientos funcionales y no funcionales, para tener la base del diseño. | E4: Documento revisado por el director, con los resultados de la encuesta, de las entrevistas y la matriz comparativa. | F4: Alta | G4: Sí | H4: 8 | I4: 2 | J4: Pendiente
A5: HU-04 | B5: Arquitectura del sistema | C5: Diseño | D5: Como estudiante, quiero definir la arquitectura cliente-servidor y las tecnologías, para tener la estructura técnica de la plataforma. | E5: Diagrama de arquitectura y tabla de tecnologías con su justificación. | F5: Alta | G5: Sí | H5: 4 | I5: 3 | J5: Pendiente
A6: HU-05 | B6: Modelo de datos | C6: Diseño | D6: Como estudiante, quiero diseñar el modelo de datos (usuarios, eventos, reservas y categorías), para guardar la información de forma ordenada. | E6: Diagrama entidad-relación y script que crea la base de datos con PostGIS. | F6: Alta | G6: Sí | H6: 4 | I6: 3 | J6: Pendiente
A7: HU-06 | B7: Prototipo de pantallas | C7: Diseño | D7: Como estudiante, quiero hacer el prototipo de las pantallas web y móvil, para validar la interfaz antes de programarla. | E7: Prototipo navegable de las historias del MVP, revisado por el director. | F7: Alta | G7: Sí | H7: 8 | I7: 4 | J7: Pendiente
A8: HU-07 | B8: Registro e inicio de sesión (organizador) | C8: Autenticación y seguridad | D8: Como organizador, quiero registrarme e iniciar sesión, para publicar mis eventos. | E8: Contraseña guardada con hash (Argon2id o bcrypt) con sal; el inicio de sesión entrega un token JWT de corta duración. | F8: Alta | G8: Sí | H8: 5 | I8: 5 | J8: Pendiente
A9: HU-08 | B9: Registro e inicio de sesión (visitante) | C9: Autenticación y seguridad | D9: Como visitante, quiero registrarme e iniciar sesión aceptando el aviso de privacidad, para usar la aplicación. | E9: Sin marcar la casilla de aceptación no se crea la cuenta; solo mayores de 18 años. | F9: Alta | G9: Sí | H9: 3 | I9: 5 | J9: Pendiente
A10: HU-09 | B10: Control de acceso por roles | C10: Autenticación y seguridad | D10: Como usuario, quiero que cada persona vea solo lo que le corresponde, para proteger la información. | E10: Un organizador solo edita sus eventos y ve sus reservas; un visitante solo ve y cancela las suyas. | F10: Alta | G10: Sí | H10: 3 | I10: 5 | J10: Pendiente
A11: HU-10 | B11: Seguridad básica | C11: Autenticación y seguridad | D11: Como estudiante, quiero aplicar las medidas básicas de seguridad, para proteger los datos de los usuarios. | E11: HTTPS, validación de datos en el servidor, consultas parametrizadas, límite de intentos de inicio de sesión y secretos en variables de entorno. | F11: Alta | G11: Sí | H11: 3 | I11: 5 | J11: Pendiente
A12: HU-11 | B12: Crear evento | C12: Gestión de eventos | D12: Como organizador, quiero crear un evento con título, fecha, lugar, categoría y cupos, para que los visitantes lo vean. | E12: El evento queda guardado y aparece en mi lista de eventos. | F12: Alta | G12: Sí | H12: 5 | I12: 6 | J12: Pendiente
A13: HU-12 | B13: Editar y deshabilitar evento | C13: Gestión de eventos | D13: Como organizador, quiero editar y deshabilitar mis eventos, para mantener la información al día. | E13: Los eventos deshabilitados dejan de verse para los visitantes. | F13: Alta | G13: Sí | H13: 3 | I13: 6 | J13: Pendiente
... A38: HU-37 | B38: Registro del software y entrega final | C38: Documentos y cierre | D38: Como estudiante, quiero tramitar la solicitud de registro del software por medio de la institución, para protegerlo como soporte lógico. | E38: Solicitud de registro ante la Dirección Nacional de Derechos de Autor presentada y entrega final realizada. | F38: Alta | G38: Sí | H38: 3 | I38: 11 | J38: Pendiente
A39: HU-38 | B39: Favoritos | C39: Si hay tiempo | D39: Como visitante, quiero guardar eventos como favoritos, para encontrarlos después. | E39: Los favoritos se guardan en mi perfil. | F39: Baja | G39: No | H39: 3 | J39: Pendiente
A40: HU-39 | B40: Búsqueda por texto | C40: Si hay tiempo | D40: Como visitante, quiero buscar eventos por texto, para encontrarlos más rápido. | E40: La búsqueda devuelve eventos cuyo título contiene el texto. | F40: Baja | G40: No | H40: 3 | J40: Pendiente
A41: HU-40 | B41: Imagen del evento | C41: Si hay tiempo | D41: Como organizador, quiero agregar una imagen a mi evento, para hacerlo más atractivo. | E41: La imagen se muestra en la ficha del evento. | F41: Baja | G41: No | H41: 3 | J41: Pendiente
A42: HU-41 | B42: Información adicional del evento | C42: Si hay tiempo | D42: Como visitante, quiero ver precio, restricción de edad, accesibilidad y fecha de última actualización, para tener información clara (resultado de la encuesta de diagnóstico). | E42: Los campos se muestran en la ficha del evento y el organizador puede editarlos. | F42: Baja | G42: No | H42: 4 | J42: Pendiente

Sheet Sprints
A1: Sprint | B1: Inicio | C1: Fin | D1: Fase | E1: Horas disponibles | F1: Horas planificadas | G1: Diferencia | H1: Estado de la carga | I1: Horas terminadas | J1: Avance
A2: 1 | B2: 46321 | C2: =B2+13 -> 46334 | D2: Requisitos y planificación | E2: 8 | F2: =SUMIFS('Product Backlog'!$H$2:$H$60,'Product Backlog'!$I$2:$I$60,A2) -> 8 | G2: =E2-F2 -> 0 | H2: =IF(G2<0,"Sobrecargado",IF(G2=0,"Justo","Con margen")) -> Justo | I2: =SUMIFS('Product Backlog'!$H$2:$H$60,'Product Backlog'!$I$2:$I$60,A2,'Product Backlog'!$J$2:$J$60,"Terminada") -> 0 | J2: =IF(F2=0,0,I2/F2) -> 0
A3: 2 | B3: =B2+14 -> 46335 | C3: =B3+13 -> 46348 | D3: Requisitos y planificación | E3: 8 | F3: =SUMIFS('Product Backlog'!$H$2:$H$60,'Product Backlog'!$I$2:$I$60,A3) -> 8 | G3: =E3-F3 -> 0 | H3: =IF(G3<0,"Sobrecargado",IF(G3=0,"Justo","Con margen")) -> Justo | I3: =SUMIFS('Product Backlog'!$H$2:$H$60,'Product Backlog'!$I$2:$I$60,A3,'Product Backlog'!$J$2:$J$60,"Terminada") -> 0 | J3: =IF(F3=0,0,I3/F3) -> 0
A4: 3 | B4: =B3+14 -> 46349 | C4: =B4+13 -> 46362 | D4: Diseño del sistema | E4: 8 | F4: =SUMIFS('Product Backlog'!$H$2:$H$60,'Product Backlog'!$I$2:$I$60,A4) -> 8 | G4: =E4-F4 -> 0 | H4: =IF(G4<0,"Sobrecargado",IF(G4=0,"Justo","Con margen")) -> Justo | I4: =SUMIFS('Product Backlog'!$H$2:$H$60,'Product Backlog'!$I$2:$I$60,A4,'Product Backlog'!$J$2:$J$60,"Terminada") -> 0 | J4: =IF(F4=0,0,I4/F4) -> 0
A5: 4 | B5: =B4+14 -> 46363 | C5: =B5+13 -> 46376 | D5: Diseño del sistema | E5: 8 | F5: =SUMIFS('Product Backlog'!$H$2:$H$60,'Product Backlog'!$I$2:$I$60,A5) -> 8 | G5: =E5-F5 -> 0 | H5: =IF(G5<0,"Sobrecargado",IF(G5=0,"Justo","Con margen")) -> Justo | I5: =SUMIFS('Product Backlog'!$H$2:$H$60,'Product Backlog'!$I$2:$I$60,A5,'Product Backlog'!$J$2:$J$60,"Terminada") -> 0 | J5: =IF(F5=0,0,I5/F5) -> 0
A6: 5 | B6: =B5+14 -> 46377 | C6: =B6+13 -> 46390 | D6: Desarrollo del sistema | E6: 14 | F6: =SUMIFS('Product Backlog'!$H$2:$H$60,'Product Backlog'!$I$2:$I$60,A6) -> 14 | G6: =E6-F6 -> 0 | H6: =IF(G6<0,"Sobrecargado",IF(G6=0,"Justo","Con margen")) -> Justo | I6: =SUMIFS('Product Backlog'!$H$2:$H$60,'Product Backlog'!$I$2:$I$60,A6,'Product Backlog'!$J$2:$J$60,"Terminada") -> 0 | J6: =IF(F6=0,0,I6/F6) -> 0
A7: 6 | B7: =B6+14 -> 46391 | C7: =B7+13 -> 46404 | D7: Desarrollo del sistema | E7: 20 | F7: =SUMIFS('Product Backlog'!$H$2:$H$60,'Product Backlog'!$I$2:$I$60,A7) -> 20 | G7: =E7-F7 -> 0 | H7: =IF(G7<0,"Sobrecargado",IF(G7=0,"Justo","Con margen")) -> Justo | I7: =SUMIFS('Product Backlog'!$H$2:$H$60,'Product Backlog'!$I$2:$I$60,A7,'Product Backlog'!$J$2:$J$60,"Terminada") -> 0 | J7: =IF(F7=0,0,I7/F7) -> 0
A8: 7 | B8: =B7+14 -> 46405 | C8: =B8+13 -> 46418 | D8: Desarrollo del sistema | E8: 20 | F8: =SUMIFS('Product Backlog'!$H$2:$H$60,'Product Backlog'!$I$2:$I$60,A8) -> 19 | G8: =E8-F8 -> 1 | H8: =IF(G8<0,"Sobrecargado",IF(G8=0,"Justo","Con margen")) -> Con margen | I8: =SUMIFS('Product Backlog'!$H$2:$H$60,'Product Backlog'!$I$2:$I$60,A8,'Product Backlog'!$J$2:$J$60,"Terminada") -> 0 | J8: =IF(F8=0,0,I8/F8) -> 0
A9: 8 | B9: =B8+14 -> 46419 | C9: =B9+13 -> 46432 | D9: Desarrollo del sistema | E9: 20 | F9: =SUMIFS('Product Backlog'!$H$2:$H$60,'Product Backlog'!$I$2:$I$60,A9) -> 20 | G9: =E9-F9 -> 0 | H9: =IF(G9<0,"Sobrecargado",IF(G9=0,"Justo","Con margen")) -> Justo | I9: =SUMIFS('Product Backlog'!$H$2:$H$60,'Product Backlog'!$I$2:$I$60,A9,'Product Backlog'!$J$2:$J$60,"Terminada") -> 0 | J9: =IF(F9=0,0,I9/F9) -> 0
A10: 9 | B10: =B9+14 -> 46433 | C10: =B10+13 -> 46446 | D10: Pruebas y validación | E10: 14 | F10: =SUMIFS('Product Backlog'!$H$2:$H$60,'Product Backlog'!$I$2:$I$60,A10) -> 14 | G10: =E10-F10 -> 0 | H10: =IF(G10<0,"Sobrecargado",IF(G10=0,"Justo","Con margen")) -> Justo | I10: =SUMIFS('Product Backlog'!$H$2:$H$60,'Product Backlog'!$I$2:$I$60,A10,'Product Backlog'!$J$2:$J$60,"Terminada") -> 0 | J10: =IF(F10=0,0,I10/F10) -> 0
A11: 10 | B11: =B10+14 -> 46447 | C11: =B11+13 -> 46460 | D11: Pruebas y validación | E11: 14 | F11: =SUMIFS('Product Backlog'!$H$2:$H$60,'Product Backlog'!$I$2:$I$60,A11) -> 14 | G11: =E11-F11 -> 0 | H11: =IF(G11<0,"Sobrecargado",IF(G11=0,"Justo","Con margen")) -> Justo | I11: =SUMIFS('Product Backlog'!$H$2:$H$60,'Product Backlog'!$I$2:$I$60,A11,'Product Backlog'!$J$2:$J$60,"Terminada") -> 0 | J11: =IF(F11=0,0,I11/F11) -> 0
A12: 11 | B12: =B11+14 -> 46461 | C12: =B12+13 -> 46474 | D12: Entregables finales | E12: 14 | F12: =SUMIFS('Product Backlog'!$H$2:$H$60,'Product Backlog'!$I$2:$I$60,A12) -> 14 | G12: =E12-F12 -> 0 | H12: =IF(G12<0,"Sobrecargado",IF(G12=0,"Justo","Con margen")) -> Justo | I12: =SUMIFS('Product Backlog'!$H$2:$H$60,'Product Backlog'!$I$2:$I$60,A12,'Product Backlog'!$J$2:$J$60,"Terminada") -> 0 | J12: =IF(F12=0,0,I12/F12) -> 0
A13: Total | E13: =SUM(E2:E12) -> 148 | F13: =SUM(F2:F12) -> 147 | G13: =E13-F13 -> 1 | I13: =SUM(I2:I12) -> 0 | J13: =IF(F13=0,0,I13/F13) -> 0
